pai_ml/__init__.py
pai_ml/datasets/__init__.py
pai_ml/evaluate/__init__.py
pai_ml/evaluate/inspect.py
pai_ml/evaluate/loading.py
pai_ml/evaluate/comparisons/__init__.py
pai_ml/evaluate/evaluator/__init__.py
pai_ml/evaluate/evaluator/cbir.py
pai_ml/evaluate/measurements/__init__.py
pai_ml/evaluate/metrics/__init__.py
pai_ml/evaluate/metrics/first_relevant_rank/__init__.py
pai_ml/evaluate/metrics/first_relevant_rank/app.py
pai_ml/evaluate/metrics/first_relevant_rank/first_relevant_rank.py
pai_ml/evaluate/metrics/hit_at_k/__init__.py
pai_ml/evaluate/metrics/hit_at_k/app.py
pai_ml/evaluate/metrics/hit_at_k/hit_at_k.py
pai_ml/evaluate/metrics/normalized_average_rank/__init__.py
pai_ml/evaluate/metrics/normalized_average_rank/app.py
pai_ml/evaluate/metrics/normalized_average_rank/normalized_average_rank.py
pai_ml/evaluate/metrics/precision_at_k/__init__.py
pai_ml/evaluate/metrics/precision_at_k/app.py
pai_ml/evaluate/metrics/precision_at_k/precision_at_k.py
pai_ml/evaluate/metrics/recall_at_k/__init__.py
pai_ml/evaluate/metrics/recall_at_k/app.py
pai_ml/evaluate/metrics/recall_at_k/recall_at_k.py
pai_ml/evaluate/metrics/recall_at_precision/__init__.py
pai_ml/evaluate/metrics/recall_at_precision/app.py
pai_ml/evaluate/metrics/recall_at_precision/recall_at_precision.py
pai_ml/evaluate/plots/__init__.py
pai_ml/evaluate/plots/comparisons/__init__.py
pai_ml/evaluate/plots/curves/__init__.py
pai_ml/evaluate/plots/curves/precision_recall_curve.py
pai_ml/evaluate/plots/distributions/__init__.py
pai_ml/evaluate/utils/__init__.py
pai_ml/evaluate/utils/gradio.py
pai_ml/feature/__init__.py
pai_ml/feature/evaluation/__init__.py
pai_ml/feature/evaluation/base.py
pai_ml/feature/evaluation/boosting_model.py
pai_ml/feature/evaluation/ensemble_model.py
pai_ml/feature/evaluation/linear_model.py
pai_ml/feature/generation/__init__.py
pai_ml/feature/generation/hash_encoding.py
pai_ml/feature/generation/one_hot_encoding.py
pai_ml/feature/generation/target_encoding.py
pai_ml-0.1.7.dist-info/METADATA
pai_ml-0.1.7.dist-info/WHEEL
pai_ml-0.1.7.dist-info/top_level.txt
pai_ml-0.1.7.dist-info/RECORD
