Metadata-Version: 2.4
Name: pai-ml
Version: 0.1.7
Author-email: hzr <hzr@pai.com>
Requires-Python: <4.0,>=3.10
Requires-Dist: evaluate>=0.4.3
Requires-Dist: gradio>=5.33.2
Requires-Dist: matplotlib>=3.10.3
Requires-Dist: numpy<3.0.0,>=2.2.3
Requires-Dist: scikit-learn>=1.7.0
Requires-Dist: torch>=2.7.1
Requires-Dist: transformers>=4.52.4
